nepali_datetime/__init__.py
nepali_datetime/__init__.pyi
nepali_datetime/_custom_strptime.py
nepali_datetime/config.py
nepali_datetime/data/calendar_bs.csv
nepali_datetime-1.0.8.3.dist-info/METADATA
nepali_datetime-1.0.8.3.dist-info/WHEEL
nepali_datetime-1.0.8.3.dist-info/top_level.txt
nepali_datetime-1.0.8.3.dist-info/RECORD
