Metadata-Version: 2.1
Name: nepali-datetime
Version: 1.0.8.3
Summary: Datetime module that operates on top of Bikram Sambat Date & Nepal Time.
Home-page: https://github.com/amitgaru2/nepali-datetime
Author: Amit Garu <amitgaru2@gmail.com>
Author-email: amitgaru2@gmail.com
License: MIT
Keywords: nepali,bs,b.s,date,datetime,time,timezone,nepal,bikram,sambat,samvat,nepali-date,nepali-datetime,nepal-time,npt,nepal-timezone
Classifier: Programming Language :: Python :: 3
Classifier: License :: OSI Approved :: MIT License
Classifier: Operating System :: OS Independent
Requires-Python: >=3.5
